kmnet/__init__.py
kmnet/model.py
kmnet-0.1.1.dist-info/licenses/LICENSE
kmnet-0.1.1.dist-info/METADATA
kmnet-0.1.1.dist-info/WHEEL
kmnet-0.1.1.dist-info/top_level.txt
kmnet-0.1.1.dist-info/RECORD
