Metadata-Version: 2.4
Name: kmnet
Version: 0.1.1
Summary: A discrete-time survival analysis model with Kaplan-Meier inspired loss.
Home-page: https://github.com/yuvrajiro/KMNet
Author: Yuvraj
Author-email: yuvraj@gmail.com
Project-URL: Bug Tracker, https://github.com/yuvrajiro/KMNet/issues
Classifier: Programming Language :: Python :: 3
Classifier: License :: OSI Approved :: MIT License
Classifier: Operating System :: OS Independent
Classifier: Topic :: Scientific/Engineering :: Artificial Intelligence
Classifier: Topic :: Scientific/Engineering :: Medical Science Apps.
Requires-Python: >=3.7
License-File: LICENSE
Requires-Dist: torch>=1.7.0
Requires-Dist: numpy
Requires-Dist: pandas
Requires-Dist: torchtuples
Requires-Dist: pycox
Requires-Dist: numba
Dynamic: author
Dynamic: author-email
Dynamic: classifier
Dynamic: description
Dynamic: description-content-type
Dynamic: home-page
Dynamic: license-file
Dynamic: project-url
Dynamic: requires-dist
Dynamic: requires-python
Dynamic: summary
